filedgr_nft_protobuf/__init__.py
filedgr_nft_protobuf/deserialize.py
filedgr_nft_protobuf/filedgr_nft_pb2.py
filedgr_nft_protobuf/serialize.py
filedgr_nft_protobuf/exceptions/__init__.py
filedgr_nft_protobuf/exceptions/custom_exceptions.py
filedgr_nft_protobuf-1.0.0.dist-info/LICENSE
filedgr_nft_protobuf-1.0.0.dist-info/METADATA
filedgr_nft_protobuf-1.0.0.dist-info/WHEEL
filedgr_nft_protobuf-1.0.0.dist-info/top_level.txt
filedgr_nft_protobuf-1.0.0.dist-info/RECORD
