Metadata-Version: 2.1
Name: filedgr-nft-protobuf
Version: 1.0.0
Summary: Serialization/Deserialization package for Filedgr NFTs
Author-email: Filedgr <code@filedgr.com>
Project-URL: repository, https://github.com/Filedgr/filedgr-nft-protobuf-python
Keywords: filedgr,nft,serialization
Classifier: License :: OSI Approved :: MIT License
Classifier: Programming Language :: Python
Classifier: Programming Language :: Python :: 3
Requires-Python: >=3.9
License-File: LICENSE
Requires-Dist: protobuf (>=4.21.9)
Provides-Extra: build
Requires-Dist: build ; extra == 'build'
Requires-Dist: twine ; extra == 'build'
Provides-Extra: dev
Requires-Dist: black ; extra == 'dev'
Requires-Dist: bumpver ; extra == 'dev'
Requires-Dist: isort ; extra == 'dev'
Requires-Dist: mypy ; extra == 'dev'
Requires-Dist: pytest ; extra == 'dev'
Requires-Dist: flake8 ; extra == 'dev'
